ocr_dataset/__init__.py
ocr_dataset/__init__.pyi
ocr_dataset/create.py
ocr_dataset/dataset.py
ocr_dataset-0.1.5.dist-info/METADATA
ocr_dataset-0.1.5.dist-info/WHEEL
ocr_dataset-0.1.5.dist-info/top_level.txt
ocr_dataset-0.1.5.dist-info/RECORD
