Metadata-Version: 2.1
Name: ocr-dataset
Version: 0.1.5
Summary: Dead simple standard for storing/loading OCR datasets (image + label pairs)
Author-email: Marcel Claramunt <marcel@moveread.com>
Project-URL: repo, https://github.com/moveread/REPO.git
Requires-Python: >=3.10
Requires-Dist: lines-dataset
Requires-Dist: files-dataset
Requires-Dist: haskellian
